spider_info_checker/__init__.py
spider_info_checker/check_info.py
spider_info_checker/checkers.py
spider_info_checker/config.py
spider_info_checker/errors.py
spider_info_checker/misc.py
spider_info_checker/models.py
spider_info_checker/templates.py
spider_info_checker/validators.py
spider_info_checker/visitors.py
spider_info_checker-0.0.11.dist-info/LICENSE
spider_info_checker-0.0.11.dist-info/METADATA
spider_info_checker-0.0.11.dist-info/WHEEL
spider_info_checker-0.0.11.dist-info/entry_points.txt
spider_info_checker-0.0.11.dist-info/top_level.txt
spider_info_checker-0.0.11.dist-info/RECORD
