Metadata-Version: 2.1
Name: spider-info-checker
Version: 0.0.11
Summary: Checks for correct spiders info
Home-page: https://github.com/pojknamn/spider_info_checker
Author: pojk
Author-email: aleksejshmel@yandex.ru
Project-URL: Source, https://github.com/pojknamn/spider_info_checker
Classifier: Programming Language :: Python :: 3
Classifier: License :: OSI Approved :: MIT License
Classifier: Operating System :: OS Independent
Requires-Python: >=3.8
License-File: LICENSE
Requires-Dist: pydantic
Requires-Dist: libcst
